ticklish_ui/__init__.py
ticklish_ui/events.py
ticklish_ui/menu_specification.py
ticklish_ui/widgets/__init__.py
ticklish_ui/widgets/application.py
ticklish_ui/widgets/buttons.py
ticklish_ui/widgets/canvas.py
ticklish_ui/widgets/checkbuttons.py
ticklish_ui/widgets/combobox.py
ticklish_ui/widgets/dropdown.py
ticklish_ui/widgets/entry.py
ticklish_ui/widgets/factories.py
ticklish_ui/widgets/frames.py
ticklish_ui/widgets/label.py
ticklish_ui/widgets/listbox.py
ticklish_ui/widgets/notebook.py
ticklish_ui/widgets/panedwindow.py
ticklish_ui/widgets/progressbar.py
ticklish_ui/widgets/radiobuttons.py
ticklish_ui/widgets/scale.py
ticklish_ui/widgets/scrollbars.py
ticklish_ui/widgets/separator.py
ticklish_ui/widgets/text.py
ticklish_ui/widgets/toplevel.py
ticklish_ui/widgets/treeview.py
ticklish_ui-0.3.0.dist-info/LICENSE
ticklish_ui-0.3.0.dist-info/METADATA
ticklish_ui-0.3.0.dist-info/WHEEL
ticklish_ui-0.3.0.dist-info/top_level.txt
ticklish_ui-0.3.0.dist-info/RECORD
