Metadata-Version: 2.1
Name: ticklish-ui
Version: 0.3.0
Summary: A thin-ish wrapper around tkinter for specifying GUIs declaratively.
Home-page: https://github.com/jasondelaat/ticklish_ui
Author: Jason DeLaat
Author-email: jason.develops@gmail.com
License: BSD 3-Clause License
Keywords: GUI,tkinter,declarative,wrapper
Platform: UNKNOWN
Classifier: Programming Language :: Python :: 3
Classifier: License :: OSI Approved :: BSD License
Classifier: Operating System :: OS Independent
Classifier: Topic :: Software Development
Classifier: Topic :: Software Development :: User Interfaces
Classifier: Topic :: Software Development :: Widget Sets
Requires-Python: >=3.6
